.gitignore
.travis.yml
CHANGELOG.rst
CONTRIBUTING.rst
LICENSE
MANIFEST.in
README.rst
gulpfile.js
manage.py
package.json
setup.py
yarn.lock
django_jet_nwmqpa.egg-info/PKG-INFO
django_jet_nwmqpa.egg-info/SOURCES.txt
django_jet_nwmqpa.egg-info/dependency_links.txt
django_jet_nwmqpa.egg-info/not-zip-safe
django_jet_nwmqpa.egg-info/requires.txt
django_jet_nwmqpa.egg-info/top_level.txt
docs/Makefile
docs/autocomplete.rst
docs/compact_inline.rst
docs/conf.py
docs/config_file.rst
docs/configuration.rst
docs/contribution.rst
docs/dashboard.rst
docs/dashboard_api.rst
docs/dashboard_custom.rst
docs/dashboard_custom_module.rst
docs/dashboard_modules.rst
docs/filters.rst
docs/getting_started.rst
docs/index.rst
docs/install.rst
docs/install_dashboard.rst
docs/make.bat
docs/_static/change_form_sibling_links.png
docs/_static/compact_inline.png
docs/_static/dashboard_module_app_list.png
docs/_static/dashboard_module_feed.png
docs/_static/dashboard_module_google_analytics.png
docs/_static/dashboard_module_link_list.png
docs/_static/dashboard_module_model_list.png
docs/_static/dashboard_module_recent_actions.png
docs/_static/dashboard_module_settings.png
docs/_static/dashboard_module_yandex_metrika.png
docs/_static/side_menu_compact.png
docs/_static/themes.png
jet/__init__.py
jet/admin.py
jet/filters.py
jet/forms.py
jet/models.py
jet/ordered_set.py
jet/settings.py
jet/urls.py
jet/utils.py
jet/views.py
jet/dashboard/__init__.py
jet/dashboard/dashboard.py
jet/dashboard/forms.py
jet/dashboard/models.py
jet/dashboard/modules.py
jet/dashboard/settings.py
jet/dashboard/urls.py
jet/dashboard/utils.py
jet/dashboard/views.py
jet/dashboard/dashboard_modules/__init__.py
jet/dashboard/dashboard_modules/google_analytics.py
jet/dashboard/dashboard_modules/google_analytics_views.py
jet/dashboard/dashboard_modules/yandex_metrika.py
jet/dashboard/dashboard_modules/yandex_metrika_views.py
jet/dashboard/locale/ar/LC_MESSAGES/django.mo
jet/dashboard/locale/ar/LC_MESSAGES/django.po
jet/dashboard/locale/ar/LC_MESSAGES/djangojs.mo
jet/dashboard/locale/ar/LC_MESSAGES/djangojs.po
jet/dashboard/locale/cs/LC_MESSAGES/django.mo
jet/dashboard/locale/cs/LC_MESSAGES/django.po
jet/dashboard/locale/cs/LC_MESSAGES/djangojs.mo
